<?xml version="1.0" encoding="utf-8" ?>
<dwsync>
<file name="b.png" server="ayopeduli.com/public_html/newversion/" local="129553191700000000" remote="130323288600000000" />
<file name="bl.png" server="ayopeduli.com/public_html/newversion/" local="129553191700000000" remote="130323288600000000" />
<file name="br.png" server="ayopeduli.com/public_html/newversion/" local="129553191700000000" remote="130323288600000000" />
<file name="closelabel.gif" server="ayopeduli.com/public_html/newversion/" local="129553191700000000" remote="130323288600000000" />
<file name="loading.gif" server="ayopeduli.com/public_html/newversion/" local="129553191700000000" remote="130323288600000000" />
<file name="shadow.gif" server="ayopeduli.com/public_html/newversion/" local="129553191700000000" remote="130323288600000000" />
<file name="Thumbs.db" server="ayopeduli.com/public_html/newversion/" local="129556469440000000" remote="130323288600000000" />
<file name="tl.png" server="ayopeduli.com/public_html/newversion/" local="129553191700000000" remote="130323288600000000" />
<file name="tr.png" server="ayopeduli.com/public_html/newversion/" local="129553191700000000" remote="130323288600000000" />
</dwsync>